CHANGELOG
LICENSE
MANIFEST.in
README.md
README.rst
VERSION
aeneas_check_setup.py
requirements.txt
setup.py
setupmeta.py
aeneas/README.md
aeneas/__init__.py
aeneas/adjustboundaryalgorithm.py
aeneas/analyzecontainer.py
aeneas/audiofile.py
aeneas/audiofilemfcc.py
aeneas/cewsubprocess.py
aeneas/configuration.py
aeneas/container.py
aeneas/diagnostics.py
aeneas/downloader.py
aeneas/dtw.py
aeneas/exacttiming.py
aeneas/executejob.py
aeneas/executetask.py
aeneas/ffmpegwrapper.py
aeneas/ffprobewrapper.py
aeneas/globalconstants.py
aeneas/globalfunctions.py
aeneas/hierarchytype.py
aeneas/idsortingalgorithm.py
aeneas/job.py
aeneas/language.py
aeneas/logger.py
aeneas/mfcc.py
aeneas/plotter.py
aeneas/runtimeconfiguration.py
aeneas/sd.py
aeneas/synthesizer.py
aeneas/task.py
aeneas/textfile.py
aeneas/tree.py
aeneas/vad.py
aeneas/validator.py
aeneas/wavfile.py
aeneas.egg-info/PKG-INFO
aeneas.egg-info/SOURCES.txt
aeneas.egg-info/dependency_links.txt
aeneas.egg-info/requires.txt
aeneas.egg-info/top_level.txt
aeneas/cdtw/.gitignore
aeneas/cdtw/Makefile
aeneas/cdtw/README.md
aeneas/cdtw/__init__.py
aeneas/cdtw/cdtw_driver.c
aeneas/cdtw/cdtw_func.c
aeneas/cdtw/cdtw_func.h
aeneas/cdtw/cdtw_py.c
aeneas/cdtw/cdtw_setup.py
aeneas/cew/.gitignore
aeneas/cew/Makefile
aeneas/cew/README.md
aeneas/cew/__init__.py
aeneas/cew/cew_driver.c
aeneas/cew/cew_func.c
aeneas/cew/cew_func.h
aeneas/cew/cew_py.c
aeneas/cew/cew_setup.py
aeneas/cew/speak_lib.h
aeneas/cfw/.gitignore
aeneas/cfw/Makefile
aeneas/cfw/README.md
aeneas/cfw/__init__.py
aeneas/cfw/cfw_driver.cc
aeneas/cfw/cfw_func.cc
aeneas/cfw/cfw_func.h
aeneas/cfw/cfw_py.cc
aeneas/cfw/cfw_setup.py
aeneas/cfw/festival/ModuleDescription.h
aeneas/cfw/festival/Phone.h
aeneas/cfw/festival/festival.h
aeneas/cfw/festival/fngram.h
aeneas/cfw/festival/intonation.h
aeneas/cfw/festival/lexicon.h
aeneas/cfw/festival/module_support.h
aeneas/cfw/festival/modules.h
aeneas/cfw/festival/text.h
aeneas/cfw/speech_tools/EST.h
aeneas/cfw/speech_tools/EST_ChannelType.h
aeneas/cfw/speech_tools/EST_Chunk.h
aeneas/cfw/speech_tools/EST_Complex.h
aeneas/cfw/speech_tools/EST_Contents.h
aeneas/cfw/speech_tools/EST_DMatrix.h
