Metadata-Version: 1.1
Name: aeneas
Version: 1.7.0.0
Summary: aeneas is a Python/C library and a set of tools to automagically synchronize audio and text (aka forced alignment)
Home-page: https://github.com/readbeyond/aeneas
Author: Alberto Pettarin
Author-email: alberto@albertopettarin.it
License: GNU Affero General Public License v3 (AGPL v3)
Keywords: AUD,AWS Polly TTS API,CSV,DTW,EAF,ELAN,EPUB 3 Media Overlay,EPUB 3,EPUB,Festival,JSON,MFCC,Mel-frequency cepstral coefficients,Nuance TTS API,ReadBeyond Sync,ReadBeyond,SBV,SMIL,SRT,SSV,SUB,TGT,TSV,TTML,TTS,TextGrid,VTT,XML,aeneas,audio/text alignment,dynamic time warping,eSpeak,eSpeak-ng,espeak,espeak-ng,festival,ffmpeg,ffprobe,forced alignment,media overlay,rb_smil_emulator,speech to text,subtitles,sync,synchronization,text to speech,text2wave,tts
Platform: UNKNOWN
Classifier: Development Status :: 5 - Production/Stable
Classifier: Environment :: Console
Classifier: Intended Audience :: Developers
Classifier: Intended Audience :: Education
Classifier: Intended Audience :: End Users/Desktop
Classifier: Intended Audience :: Science/Research
Classifier: License :: OSI Approved :: GNU Affero General Public License v3
Classifier: Natural Language :: English
Classifier: Operating System :: MacOS :: MacOS X
Classifier: Operating System :: Microsoft :: Windows
Classifier: Operating System :: POSIX :: Linux
Classifier: Programming Language :: C
Classifier: Programming Language :: Python
Classifier: Programming Language :: Python :: 2
Classifier: Programming Language :: Python :: 2.7
Classifier: Programming Language :: Python :: 3
Classifier: Programming Language :: Python :: 3.4
Classifier: Programming Language :: Python :: 3.5
Classifier: Topic :: Education
Classifier: Topic :: Multimedia
Classifier: Topic :: Multimedia :: Sound/Audio
Classifier: Topic :: Multimedia :: Sound/Audio :: Analysis
Classifier: Topic :: Multimedia :: Sound/Audio :: Speech
Classifier: Topic :: Printing
Classifier: Topic :: Scientific/Engineering
Classifier: Topic :: Scientific/Engineering :: Mathematics
Classifier: Topic :: Software Development :: Libraries :: Python Modules
Classifier: Topic :: Text Processing
Classifier: Topic :: Text Processing :: Linguistic
Classifier: Topic :: Text Processing :: Markup
Classifier: Topic :: Text Processing :: Markup :: HTML
Classifier: Topic :: Text Processing :: Markup :: XML
Classifier: Topic :: Utilities
